aeneas/README.md
aeneas/__init__.py
aeneas/adjustboundaryalgorithm.py
aeneas/analyzecontainer.py
aeneas/audiofile.py
aeneas/audiofilemfcc.py
aeneas/cewsubprocess.py
aeneas/configuration.py
aeneas/container.py
aeneas/diagnostics.py
aeneas/downloader.py
aeneas/dtw.py
aeneas/exacttiming.py
aeneas/executejob.py
aeneas/executetask.py
aeneas/ffmpegwrapper.py
aeneas/ffprobewrapper.py
aeneas/globalconstants.py
aeneas/globalfunctions.py
aeneas/hierarchytype.py
aeneas/idsortingalgorithm.py
aeneas/job.py
aeneas/language.py
aeneas/logger.py
aeneas/mfcc.py
aeneas/plotter.py
aeneas/runtimeconfiguration.py
aeneas/sd.py
aeneas/synthesizer.py
aeneas/task.py
aeneas/textfile.py
aeneas/tree.py
aeneas/vad.py
aeneas/validator.py
aeneas/wavfile.py
aeneas/cdtw/README.md
aeneas/cdtw/__init__.py
aeneas/cdtw/cdtw.cpython-36m-x86_64-linux-gnu.so
aeneas/cdtw/cdtw_driver.c
aeneas/cdtw/cdtw_func.c
aeneas/cdtw/cdtw_func.h
aeneas/cdtw/cdtw_py.c
aeneas/cdtw/cdtw_setup.py
aeneas/cew/README.md
aeneas/cew/__init__.py
aeneas/cew/cew.cpython-36m-x86_64-linux-gnu.so
aeneas/cew/cew_func.h
aeneas/cew/cew_setup.py
aeneas/cew/speak_lib.h
aeneas/cfw/__init__.py
aeneas/cfw/cfw_setup.py
aeneas/cmfcc/README.md
aeneas/cmfcc/__init__.py
aeneas/cmfcc/cmfcc.cpython-36m-x86_64-linux-gnu.so
aeneas/cmfcc/cmfcc_driver.c
aeneas/cmfcc/cmfcc_func.c
aeneas/cmfcc/cmfcc_func.h
aeneas/cmfcc/cmfcc_py.c
aeneas/cmfcc/cmfcc_setup.py
aeneas/cwave/README.md
aeneas/cwave/__init__.py
aeneas/cwave/cwave_driver.c
aeneas/cwave/cwave_func.c
aeneas/cwave/cwave_func.h
aeneas/cwave/cwave_py.c
aeneas/cwave/cwave_setup.py
aeneas/extra/README.md
aeneas/extra/__init__.py
aeneas/extra/ctw_espeak.py
aeneas/extra/ctw_speect.py
aeneas/res/LiberationMono-Regular.ttf
aeneas/res/__init__.py
aeneas/res/finetuneas.html
aeneas/syncmap/__init__.py
aeneas/syncmap/format.py
aeneas/syncmap/fragment.py
aeneas/syncmap/fragmentlist.py
aeneas/syncmap/headtailformat.py
aeneas/syncmap/missingparametererror.py
aeneas/syncmap/smfaudacity.py
aeneas/syncmap/smfbase.py
py3_aeneas-1.1.0.dist-info/LICENSE
py3_aeneas-1.1.0.dist-info/METADATA
py3_aeneas-1.1.0.dist-info/WHEEL
py3_aeneas-1.1.0.dist-info/top_level.txt
py3_aeneas-1.1.0.dist-info/RECORD
